evaluation_embedder/__init__.py
evaluation_embedder/py.typed
evaluation_embedder/src/__init__.py
evaluation_embedder/src/connectors/__init__.py
evaluation_embedder/src/connectors/minio.py
evaluation_embedder/src/connectors/parquet.py
evaluation_embedder/src/constants.py
evaluation_embedder/src/datasets/__init__.py
evaluation_embedder/src/datasets/mixins.py
evaluation_embedder/src/datasets/polars.py
evaluation_embedder/src/datasets/preprocess/__init__.py
evaluation_embedder/src/datasets/preprocess/preprocess.py
evaluation_embedder/src/datasets/preprocess/token_counter.py
evaluation_embedder/src/evaluation/__init__.py
evaluation_embedder/src/evaluation/async_batcher.py
evaluation_embedder/src/evaluation/embedders.py
evaluation_embedder/src/evaluation/evaluators.py
evaluation_embedder/src/evaluation/processors.py
evaluation_embedder/src/evaluation/rerankers.py
evaluation_embedder/src/evaluation/retrievers.py
evaluation_embedder/src/evaluation/scores.py
evaluation_embedder/src/evaluation/vector_stores.py
evaluation_embedder/src/ingestion/__init__.py
evaluation_embedder/src/ingestion/base_ingestion.py
evaluation_embedder/src/mixins.py
evaluation_embedder/src/settings.py
evaluation_embedder/src/utils.py
evaluation_embedder-1.3.2.dist-info/METADATA
evaluation_embedder-1.3.2.dist-info/WHEEL
evaluation_embedder-1.3.2.dist-info/RECORD
