Metadata-Version: 2.4
Name: evaluation-embedder
Version: 1.3.2
Summary: 
Author: jalal
Author-email: jalalkhaldi3@gmail.com
Requires-Python: >=3.10,<3.13
Classifier: Programming Language :: Python :: 3
Classifier: Programming Language :: Python :: 3.10
Classifier: Programming Language :: Python :: 3.11
Classifier: Programming Language :: Python :: 3.12
Requires-Dist: faiss-cpu (>=1.13.2,<2.0.0)
Requires-Dist: langchain (>=1.2.3,<2.0.0)
Requires-Dist: minio (>=7.2.20,<8.0.0)
Requires-Dist: numpy (>=1.24,<2.3)
Requires-Dist: openai (>=2.15.0,<3.0.0)
Requires-Dist: polars (>=1.37.1,<2.0.0)
Requires-Dist: pydantic-settings (>=2.12.0,<3.0.0)
Requires-Dist: qdrant-client (>=1.16.1,<2.0.0)
Requires-Dist: rank-bm25 (>=0.2.2,<0.3.0)
Requires-Dist: torch (>=2.9.0,<3.0.0)
Requires-Dist: transformers (>=4.57.6,<5.0.0)
